Workbook

Sheet CONTAS
A1: PROGRAMAÇÃO DE CONTAS
A2: MÊS REFERENCIA | B2: 45566 | C2: 45597 | D2: 45627 | E2: 45658 | F2: 45689 | G2: 45717 | H2: 45748 | I2: 45778 | J2: 45809 | K2: 45839 | L2: 45870 | M2: 45901 | N2: 45931 | O2: 45962 | P2: 45992 | Q2: JANEIRO | R2: FEVEREIRO | S2: MARÇO | T2: ABRIL | U2: MAIO | V2: JUNHO | W2: JULHO | X2: AGOSTO | Y2: SETEMBRO | Z2: OUTUBRO | AA2: NOVEMBRO | AB2: DEZEMBRO
A3: CELULAR DA FRAN | C3: 322.15 | D3: 306.83 | E3: 306.32 | F3: 331.76 | G3: 306.32 | H3: 306.32 | I3: 151.73 | J3: 169.75 | K3: 151.73 | L3: 151.73 | M3: 170.29 | N3: 151.73 | O3: 151.73 | P3: 151.73 | Q3: 151.73 | R3: 151.73 | S3: 151.73 | T3: 151.73 | U3: 151.73 | AC3: Vai ate 05/2026
A4: SOFÁ | I4: 227.04 | J4: 227.04 | K4: 227.04 | L4: 227.04 | M4: 258.26 | N4: 227.04 | O4: 227.04 | P4: 227.04 | Q4: 227.04 | R4: 227.04 | S4: 227.04 | T4: 227.04 | U4: 227.04 | V4: 227.04 | W4: 227.04 | X4: 227.04 | Y4: 227.04 | Z4: 227.04 | AC4: Vai ate 10/2026
A5: INTERNET | D5: 407.36 | E5: 129.9 | F5: 129.9 | G5: 129.9 | H5: 129.9 | I5: 129.9 | J5: 132.57 | K5: 129.9 | L5: 129.9 | M5: 129.9 | N5: 129.9 | R5: 90 | S5: 90 | T5: 90 | U5: 90 | V5: 90 | W5: 90 | X5: 90 | Y5: 90 | Z5: 90 | AA5: 90 | AB5: 90
A6: SEMAE | D6: 113.49 | E6: 42.38 | F6: 240.25 | G6: 91.04 | H6: 154.62 | I6: 117.72 | J6: 113.6 | K6: 59.12 | N6: 86 | Q6: 98.86 | R6: 76.9 | S6: 63.98 | T6: 63.98
A7: CPFL | D7: 119.25 | E7: 104.22 | G7: 127.45 | I7: 285.83 | J7: 144.05 | N7: 74.83 | Q7: 126.41 | R7: 199.49 | S7: 11 | T7: 11
A8: CARTÃO MAIS | E8: 407.15 | F8: 407.15 | G8: 407.15 | H8: 407.15 | I8: 407.15 | J8: 407.15 | K8: 437.12 | L8: 407.15 | M8: 407.15 | N8: 436.99 | O8: 436.99 | P8: 436.99 | Q8: 436.99 | R8: 407.15 | S8: 407.15 | T8: 407.15 | AC8: Faltam 1(FEITA EM 16X)
A9: NUBANK | I9: 268.31 | J9: 268.31
A10: MARIA ANTONIA | E10: 100 | F10: 140 | J10: 79 | K10: 95 | L10: 95 | M10: 95 | N10: 100 | O10: 100 | P10: 100 | Q10: 200 | R10: 100 | S10: 100 | T10: 100 | U10: 100 | V10: 100 | W10: 100 | X10: 115 | AC10: Faltam 510
A11: JAQUELINE | C11: 27 | E11: 28.9 | F11: 28.9 | G11: 28.9 | H11: 28.9 | I11: 28.9 | J11: 28.9 | K11: 28.9 | L11: 28.9 | M11: 28.9 | N11: 28.9 | O11: 28.9 | P11: 28.9 | Q11: 28.9 | R11: 28.9 | S11: 28.9 | T11: 28.9 | U11: 28.9 | V11: 28.9 | W11: 28.9 | X11: 28.9 | Y11: 28.9 | Z11: 28.9 | AA11: 28.9 | AB11: 28.9
A12: EMPRÉSTIMO PAI | B12: 728.49 | C12: 728.49 | D12: 728.49 | E12: 728.49 | F12: 728.49 | G12: 728.49 | H12: 728.49 | I12: 528.49 | J12: 528.49 | K12: 728.49 | L12: 728.49 | M12: 728.49 | N12: 728.49 | O12: 728.49 | P12: 360 | Q12: 360 | R12: 360 | S12: 360 | T12: 360 | U12: 360 | V12: 360 | W12: 360 | X12: 360 | Y12: 360 | Z12: 360 | AA12: 360 | AB12: 360 | AC12: Falta 17 (FEITA EM 36X)
A13: EMPRÉSTIMO PAI | S13: 200 | T13: 200 | U13: 200 | V13: 200 | W13: 200 | X13: 200 | Y13: 200 | Z13: 200 | AA13: 200 | AB13: 200 | AC13: Falta 24 (FEITA EM 48X)
A14: SHOPEE | S14: 87.53 | T14: 89.82 | U14: 89.82 | V14: 89.82 | W14: 89.82 | X14: 89.82 | Y14: 89.82 | Z14: 89.82 | AA14: 89.82 | AB14: 89.82 | AC14: Falta 11 (FEITA EM 12X)
A15: ALINE (GABRIEL) | S15: 140 | AC15: Falta 01 (FEITA EM 03X)
A16: CABELO DA FRAN | P16: 150 | Q16: 150 | R16: 150 | S16: 108.42 | AC16: Faltam 1 parcelas
A17: VIDEOGAME | P17: 250 | Q17: 250 | R17: 250 | S17: 250 | T17: 250 | U17: 250 | V17: 250 | W17: 250 | X17: 250 | AC17: Faltam 05 (FEITA EM 06X)
A18: VIVO FRAN | C18: 64.99 | E18: 66.12 | F18: 55 | G18: 55 | H18: 55 | I18: 55 | J18: 55 | K18: 55 | L18: 55 | M18: 55 | N18: 55 | O18: 55 | P18: 64 | Q18: 64 | R18: 85 | S18: 64 | T18: 64 | U18: 64 | V18: 64 | W18: 64 | X18: 64 | Y18: 64 | Z18: 64 | AA18: 64 | AB18: 64
A19: FARMACIA | T19: 80 | U19: 80 | V19: 80 | W19: 80 | X19: 80 | Y19: 80 | Z19: 80 | AA19: 80 | AB19: 80
A20: PSICOLOGA | N20: 300 | O20: 240 | P20: 300 | Q20: 240 | R20: 240 | S20: 240 | T20: 300 | U20: 300 | V20: 300 | W20: 300 | X20: 300 | Y20: 300 | Z20: 300 | AA20: 300 | AB20: 300
A21: SOBRANCELHA | S21: 40 | T21: 40 | U21: 40 | V21: 40 | W21: 40 | X21: 40 | Y21: 40 | Z21: 40 | AA21: 40 | AB21: 40
A22: GASTOS EM CAMPINAS | T22: 300
A23: SARA | T23: 89.99 | U23: 89.99 | AC23: 20/04 e 20/05
A24: CORTE DE CABELO | T24: 30 | U24: 60 | V24: 60 | W24: 60 | X24: 60 | Y24: 60 | Z24: 60 | AA24: 60 | AB24: 60
A25: CURSO | T25: 161.39 | U25: 161.39 | V25: 161.39 | W25: 161.39 | X25: 161.39 | Y25: 161.39 | Z25: 161.39 | AA25: 161.39 | AC25: Faltam 08 (FEITA EM 08x)
A26: CANAL TV | T26: 30 | U26: 30 | V26: 30 | W26: 30 | X26: 30 | Y26: 30 | Z26: 30 | AA26: 30 | AB26: 30
A27: ACADEMIA | T27: 170 | U27: 170 | V27: 170 | W27: 170 | X27: 170 | Y27: 170 | Z27: 170 | AA27: 170 | AB27: 170
A28: SUPERMERCADO | T28: 550 | U28: 500
A29: TESTE | T29: 10000
A30: TOTAL DE CONTAS | R30: =SUM(R3:R25) -> 2366.21 | S30: =SUM(S3:S22) -> 2569.75 | T30: =SUM(T3:T29) -> 13795 | U30: =SUM(U3:U28) -> 2992.87 | V30: =SUM(V3:V28) -> 2251.15 | W30: =SUM(W3:W28) -> 2251.15 | X30: =SUM(X3:X28) -> 2266.15 | Y30: =SUM(Y3:Y28) -> 1901.15 | Z30: =SUM(Z3:Z28) -> 1901.15 | AA30: =SUM(AA3:AA28) -> 1674.11 | AB30: =SUM(AB3:AB28) -> 1512.72
L35: divórcio
L36: NUBANK

Sheet GANHO MENSAL
B2: GANHO MENSAL
B3: MÊS REF | C3: SALARIO | D3: SEGURO | E3: ABONO SALARIAL | F3: RESERVA ATUAL NO SANTANDER
B5: MARÇO | C5: 2637.32 | F5: 4300
B6: ABRIL | C6: 2100 | D6: 1892.07 | E6: 1216 | G6: 46113
B7: MAIO | C7: 2100 | D7: 1892.07 | E7: 1621 | G7: 46143
B8: JUNHO | C8: 2100 | D8: 1892.07 | G8: 46173
B9: JULHO | C9: 2100 | D9: 1892.07 | G9: 46203
B10: AGOSTO | C10: 2100 | D10: 1892.07 | G10: 46233
B11: SETEMBRO | C11: 2100
B12: OUTUBRO | C12: 2100
B13: NOVEMBRO | C13: 2100
B14: DEZEMBRO | C14: 2100
B15: JANEIRO | C15: 2100
B17: RECEITA BRUTA MENSAL
B18: MÊS REF | C18: ENTRADA | D18: SAÍDA | E18: TOTAL | F18: PREVISÃO POUPANÇA
B20: MARÇO | C20: =SUM('GANHO MENSAL'!C5:E5) -> 2637.32 | D20: =_xlfn.XLOOKUP(B20,CONTAS!$2:$2,CONTAS!$30:$30,0,0) -> 2569.75 | E20: =C20-D20 -> 67.57 | F20: 4333
B21: ABRIL | C21: =SUM('GANHO MENSAL'!C6:E6) -> 5208.07 | D21: =_xlfn.XLOOKUP(B21,CONTAS!$2:$2,CONTAS!$30:$30,0,0) -> 13795 | E21: =C21-D21 -> -8586.93 | F21: =SUM(F20,E21) -> -4253.93
B22: MAIO | C22: =SUM('GANHO MENSAL'!C7:E7) -> 5613.07 | D22: =_xlfn.XLOOKUP(B22,CONTAS!$2:$2,CONTAS!$30:$30,0,0) -> 2992.87 | E22: =C22-D22 -> 2620.2 | F22: =SUM(F21,E22) -> -1633.73
B23: JUNHO | C23: =SUM('GANHO MENSAL'!C8:D8) -> 3992.07 | D23: =_xlfn.XLOOKUP(B23,CONTAS!$2:$2,CONTAS!$30:$30,0,0) -> 2251.15 | E23: =C23-D23 -> 1740.92 | F23: =SUM(F22,E23) -> 107.19
B24: JULHO | C24: =SUM('GANHO MENSAL'!C9:D9) -> 3992.07 | D24: =_xlfn.XLOOKUP(B24,CONTAS!$2:$2,CONTAS!$30:$30,0,0) -> 2251.15 | E24: =C24-D24 -> 1740.92 | F24: =SUM(F23,E24) -> 1848.11
B25: AGOSTO | C25: =SUM('GANHO MENSAL'!C10:D10) -> 3992.07 | D25: =_xlfn.XLOOKUP(B25,CONTAS!$2:$2,CONTAS!$30:$30,0,0) -> 2266.15 | E25: =C25-D25 -> 1725.92 | F25: =SUM(F24,E25) -> 3574.03
B26: SETEMBRO | C26: =SUM('GANHO MENSAL'!C11:E11) -> 2100 | D26: =_xlfn.XLOOKUP(B26,CONTAS!$2:$2,CONTAS!$30:$30,0,0) -> 1901.15 | E26: =C26-D26 -> 198.85 | F26: =SUM(F25,E26) -> 3772.88
B27: OUTUBRO | C27: =SUM('GANHO MENSAL'!C12:E12) -> 2100 | D27: =_xlfn.XLOOKUP(B27,CONTAS!$2:$2,CONTAS!$30:$30,0,0) -> 1901.15 | E27: =C27-D27 -> 198.85 | F27: =SUM(F26,E27) -> 3971.73
B28: NOVEMBRO | C28: =SUM('GANHO MENSAL'!C13:E13) -> 2100 | D28: =_xlfn.XLOOKUP(B28,CONTAS!$2:$2,CONTAS!$30:$30,0,0) -> 1674.11 | E28: =C28-D28 -> 425.89 | F28: =SUM(F27,E28) -> 4397.62
B29: DEZEMBRO | C29: =SUM('GANHO MENSAL'!C14:E14) -> 2100 | D29: =_xlfn.XLOOKUP(B29,CONTAS!$2:$2,CONTAS!$30:$30,0,0) -> 1512.72 | E29: =C29-D29 -> 587.28 | F29: =SUM(F28,E29) -> 4984.9

Sheet GASTOS 
A1: CATEGORIA | B1: TOTAL DE GASTOS MARÇO
A2: DINHEIRO | B2: =SUMIF(E13:E56,"DINHEIRO",D13:D56) -> 1671.99
A3: REFEIÇÃO | B3: =SUMIF(E13:E56,"REFEIÇÃO",D13:D56) -> 561.63
A4: VALOR TOTAL | B4: =SUM(B2:B3) -> 2233.62
A6: CATEGORIA | B6: TOTAL DE GASTOS ABRIL
A7: DINHEIRO | B7: =SUMIF(E57:E80,"DINHEIRO",D57:D80) -> 330.93
A8: REFEIÇÃO | B8: =SUMIF(D57:E80,"REFEIÇÃO",D57:D80) -> 0
A9: VALOR TOTAL | B9: =SUM(B7+B8) -> 330.93
A12: DATA | B12: MES | C12: LOCAL GASTO | D12: VALOR | E12: FONTE DE SAIDA | F12: Coluna 1
A13: 11/03/0206 | B13: MARÇO | C13: Saída Fran | D13: 20 | E13: DINHEIRO | F13: =IF(D13>100,"ATENÇÃO","OK") -> OK
A14: 11/03/0206 | B14: MARÇO | C14: Cabelo Gabriel | D14: 30 | E14: DINHEIRO | F14: =IF(D14>100,"ATENÇÃO","OK") -> OK
A15: 11/03/0206 | B15: MARÇO | C15: Contas | D15: 125.79 | E15: DINHEIRO | F15: =IF(D15>100,"ATENÇÃO","OK") -> ATENÇÃO
A16: 11/03/0206 | B16: MARÇO | C16: Contas | D16: 63.98 | E16: DINHEIRO | F16: =IF(D16>100,"ATENÇÃO","OK") -> OK
A17: 46087 | B17: MARÇO | C17: Supermercado | D17: 86.44 | E17: REFEIÇÃO | F17: =IF(D17>100,"ATENÇÃO","OK") -> OK
A18: 46088 | B18: MARÇO | C18: Pizza Hut | D18: 51.6 | E18: REFEIÇÃO | F18: =IF(D18>100,"ATENÇÃO","OK") -> OK
A19: 46088 | B19: MARÇO | C19: Churros | D19: 28 | E19: REFEIÇÃO | F19: =IF(D19>100,"ATENÇÃO","OK") -> OK
A20: 46088 | B20: MARÇO | C20: Supermercado | D20: 212.67 | E20: REFEIÇÃO | F20: =IF(D20>100,"ATENÇÃO","OK") -> ATENÇÃO
A21: 46088 | B21: MARÇO | C21: Taxa Ubatuba | D21: 41.58 | E21: DINHEIRO | F21: =IF(D21>100,"ATENÇÃO","OK") -> OK
A22: 46088 | B22: MARÇO | C22: Padaria | D22: 13.42 | E22: DINHEIRO | F22: =IF(D22>100,"ATENÇÃO","OK") -> OK
A23: 46089 | B23: MARÇO | C23: Arredondamento | D23: 1.6 | E23: DINHEIRO | F23: =IF(D23>100,"ATENÇÃO","OK") -> OK
A24: 46089 | B24: MARÇO | C24: Açai | D24: 36.68 | E24: REFEIÇÃO | F24: =IF(D24>100,"ATENÇÃO","OK") -> OK
A25: 46090 | B25: MARÇO | C25: Multa | D25: 296.4 | E25: DINHEIRO | F25: =IF(D25>100,"ATENÇÃO","OK") -> ATENÇÃO
A26: 46090 | B26: MARÇO | C26: Contas | D26: 83.16 | E26: DINHEIRO | F26: =IF(D26>100,"ATENÇÃO","OK") -> OK
A27: 46090 | B27: MARÇO | C27: Padaria | D27: 13.42 | E27: DINHEIRO | F27: =IF(D27>100,"ATENÇÃO","OK") -> OK
A28: 46090 | B28: MARÇO | C28: Jessica Rauany | D28: 22.47 | E28: DINHEIRO | F28: =IF(D28>100,"ATENÇÃO","OK") -> OK
... A59: 46114 | B59: ABRIL | C59: Inga | D59: 4 | E59: DINHEIRO | F59: =IF(D59>100,"ATENÇÃO","OK") -> OK
A60: 02/04/0206 | B60: ABRIL | C60: Ifood | D60: 52.18 | E60: DINHEIRO | F60: =IF(D60>100,"ATENÇÃO","OK") -> OK
A61: 46115 | B61: ABRIL | C61: Supermercado | D61: 39.4 | E61: DINHEIRO | F61: =IF(D61>100,"ATENÇÃO","OK") -> OK
A62: 46116 | B62: ABRIL | C62: Geraldo | D62: 7 | E62: DINHEIRO | F62: =IF(D62>100,"ATENÇÃO","OK") -> OK
A63: 04/04/0206 | B63: ABRIL | C63: Ifood | D63: 38.48 | E63: DINHEIRO | F63: =IF(D63>100,"ATENÇÃO","OK") -> OK
A64: 46118 | B64: ABRIL | C64: Gasolina | D64: 23.02 | E64: DINHEIRO | F64: =IF(D64>100,"ATENÇÃO","OK") -> OK
